{"state":{"color":"#FF0000","name":"Michigan","points":[{"lng":"-88.3713","lat":"48.3033"},{"lng":"-87.605","lat":"48.0101"},{"lng":"-84.8584","lat":"46.8902"},{"lng":"-84.765","lat":"46.6362"},{"lng":"-84.5563","lat":"46.4606"},{"lng":"-84.478","lat":"46.4525"},{"lng":"-84.445","lat":"46.4894"},{"lng":"-84.4203","lat":"46.5008"},{"lng":"-84.3956","lat":"46.4989"},{"lng":"-84.375","lat":"46.5093"},{"lng":"-84.3386","lat":"46.5069"},{"lng":"-84.2905","lat":"46.4927"},{"lng":"-84.2651","lat":"46.4951"},{"lng":"-84.2253","lat":"46.5343"},{"lng":"-84.1951","lat":"46.5404"},{"lng":"-84.1779","lat":"46.5272"},{"lng":"-84.1347","lat":"46.5348"},{"lng":"-84.1113","lat":"46.5041"},{"lng":"-84.1457","lat":"46.4189"},{"lng":"-84.1395","lat":"46.372"},{"lng":"-84.1058","lat":"46.3218"},{"lng":"-84.1203","lat":"46.3147"},{"lng":"-84.1148","lat":"46.2672"},{"lng":"-84.0969","lat":"46.2563"},{"lng":"-84.1093","lat":"46.2411"},{"lng":"-84.0859","lat":"46.2098"},{"lng":"-84.0777","lat":"46.1879"},{"lng":"-84.0097","lat":"46.1508"},{"lng":"-84.007","lat":"46.118"},{"lng":"-83.9761","lat":"46.1018"},{"lng":"-83.9555","lat":"46.057"},{"lng":"-83.904","lat":"46.0604"},{"lng":"-83.8264","lat":"46.1185"},{"lng":"-83.7598","lat":"46.1028"},{"lng":"-83.6547","lat":"46.1218"},{"lng":"-83.5723","lat":"46.1056"},{"lng":"-83.4343","lat":"45.9993"},{"lng":"-83.5977","lat":"45.8211"},{"lng":"-82.5197","lat":"45.3396"},{"lng":"-82.1221","lat":"43.5918"},{"lng":"-82.4119","lat":"43.0112"},{"lng":"-82.4249","lat":"42.9956"},{"lng":"-82.4236","lat":"42.9579"},{"lng":"-82.4648","lat":"42.9021"},{"lng":"-82.4689","lat":"42.8543"},{"lng":"-82.4826","lat":"42.81"},{"lng":"-82.4723","lat":"42.7863"},{"lng":"-82.4847","lat":"42.7339"},{"lng":"-82.5032","lat":"42.6855"},{"lng":"-82.5108","lat":"42.638"},{"lng":"-82.5307","lat":"42.6036"},{"lng":"-82.5774","lat":"42.5672"},{"lng":"-82.5993","lat":"42.549"},{"lng":"-82.6501","lat":"42.5521"},{"lng":"-82.668","lat":"42.5354"},{"lng":"-82.7257","lat":"42.4746"},{"lng":"-82.725","lat":"42.4726"},{"lng":"-82.828","lat":"42.3738"},{"lng":"-82.944","lat":"42.3469"},{"lng":"-82.955","lat":"42.3382"},{"lng":"-83.0779","lat":"42.3098"},{"lng":"-83.1294","lat":"42.2392"},{"lng":"-83.1342","lat":"42.1741"},{"lng":"-83.1212","lat":"42.1267"},{"lng":"-83.1493","lat":"42.0411"},{"lng":"-83.1116","lat":"41.96"},{"lng":"-83.4164","lat":"41.7344"},{"lng":"-83.8724","lat":"41.7211"},{"lng":"-84.3736","lat":"41.7057"},{"lng":"-84.8062","lat":"41.6965"},{"lng":"-84.8076","lat":"41.7611"},{"lng":"-87.2067","lat":"41.7621"},{"lng":"-87.0241","lat":"42.4934"},{"lng":"-87.1477","lat":"43.3771"},{"lng":"-87.1216","lat":"43.7056"},{"lng":"-87.0474","lat":"43.9958"},{"lng":"-86.9939","lat":"44.1674"},{"lng":"-86.8662","lat":"44.472"},{"lng":"-86.6849","lat":"44.8841"},{"lng":"-86.5009","lat":"45.0813"},{"lng":"-86.2495","lat":"45.2353"},{"lng":"-86.7563","lat":"45.4438"},{"lng":"-87.0996","lat":"45.4438"},{"lng":"-87.1518","lat":"45.3772"},{"lng":"-87.171","lat":"45.3502"},{"lng":"-87.3166","lat":"45.2401"},{"lng":"-87.4059","lat":"45.2024"},{"lng":"-87.4416","lat":"45.0774"},{"lng":"-87.5912","lat":"45.091"},{"lng":"-87.6407","lat":"45.1036"},{"lng":"-87.697","lat":"45.2207"},{"lng":"-87.6476","lat":"45.3367"},{"lng":"-87.6984","lat":"45.3878"},{"lng":"-87.8494","lat":"45.3425"},{"lng":"-87.7959","lat":"45.5025"},{"lng":"-87.789","lat":"45.6726"},{"lng":"-87.9318","lat":"45.757"},{"lng":"-87.9922","lat":"45.7953"},{"lng":"-88.1186","lat":"45.8058"},{"lng":"-88.087","lat":"45.8585"},{"lng":"-88.1955","lat":"45.9531"},{"lng":"-88.3438","lat":"45.9722"},{"lng":"-88.3891","lat":"45.9836"},{"lng":"-88.5457","lat":"46.0113"},{"lng":"-88.7022","lat":"45.997"},{"lng":"-88.8135","lat":"46.0227"},{"lng":"-88.8547","lat":"46.0418"},{"lng":"-89.0936","lat":"46.1408"},{"lng":"-90.1222","lat":"46.3384"},{"lng":"-90.4175","lat":"46.5692"},{"lng":"-90.2019","lat":"46.9034"},{"lng":"-89.9547","lat":"47.2913"},{"lng":"-89.4946","lat":"48.0129"},{"lng":"-89.3381","lat":"47.9743"},{"lng":"-88.6761","lat":"48.2448"},{"lng":"-88.3726","lat":"48.3042"}]}}